{
    "1747456059.5948222": "223852270; first_name: Сергей; last_name: None; username: @kvizer; is_premium: True",
    "1747456209.8063457": "903454809; first_name: 42388; last_name: None; username: @firementat; is_premium: None",
    "1747456211.2601304": "903454809; first_name: 42388; last_name: None; username: @firementat; is_premium: None",
    "1747456223.1919024": "903454809; first_name: 42388; last_name: None; username: @firementat; is_premium: None",
    "1747456251.4706712": "223852270; first_name: Сергей; last_name: None; username: @kvizer; is_premium: True",
    "1747456294.9916523": "223852270; first_name: Сергей; last_name: None; username: @kvizer; is_premium: True",
    "1747456296.4293325": "903454809; first_name: 42388; last_name: None; username: @firementat; is_premium: None",
    "1747456300.9951217": "223852270; first_name: Сергей; last_name: None; username: @kvizer; is_premium: True",
    "1747456301.257496": "903454809; first_name: 42388; last_name: None; username: @firementat; is_premium: None",
    "1747456302.0926902": "903454809; first_name: 42388; last_name: None; username: @firementat; is_premium: None",
    "1747456302.2214599": "223852270; first_name: Сергей; last_name: None; username: @kvizer; is_premium: True",
    "1747456302.6334746": "903454809; first_name: 42388; last_name: None; username: @firementat; is_premium: None",
    "1747456302.7487903": "223852270; first_name: Сергей; last_name: None; username: @kvizer; is_premium: True",
    "1747456302.933996": "223852270; first_name: Сергей; last_name: None; username: @kvizer; is_premium: True",
    "1747456302.9805105": "903454809; first_name: 42388; last_name: None; username: @firementat; is_premium: None",
    "1747456303.1348221": "903454809; first_name: 42388; last_name: None; username: @firementat; is_premium: None",
    "1747456303.1811495": "223852270; first_name: Сергей; last_name: None; username: @kvizer; is_premium: True",
    "1747456308.1315453": "223852270; first_name: Сергей; last_name: None; username: @kvizer; is_premium: True",
    "1747456310.4028387": "223852270; first_name: Сергей; last_name: None; username: @kvizer; is_premium: True",
    "1747456311.48182": "223852270; first_name: Сергей; last_name: None; username: @kvizer; is_premium: True",
    "1747456312.2995038": "223852270; first_name: Сергей; last_name: None; username: @kvizer; is_premium: True",
    "1747456316.2845078": "223852270; first_name: Сергей; last_name: None; username: @kvizer; is_premium: True",
    "1747456318.758295": "223852270; first_name: Сергей; last_name: None; username: @kvizer; is_premium: True",
    "1747456322.9441988": "223852270; first_name: Сергей; last_name: None; username: @kvizer; is_premium: True",
    "1747456324.5214434": "223852270; first_name: Сергей; last_name: None; username: @kvizer; is_premium: True",
    "1747456337.5143888": "223852270; first_name: Сергей; last_name: None; username: @kvizer; is_premium: True",
    "1747456743.8351548": "223852270; first_name: Сергей; last_name: None; username: @kvizer; is_premium: True",
    "1747456789.1296935": "223852270; first_name: Сергей; last_name: None; username: @kvizer; is_premium: True",
    "1747456796.3182797": "223852270; first_name: Сергей; last_name: None; username: @kvizer; is_premium: True",
    "1747456802.1701272": "223852270; first_name: Сергей; last_name: None; username: @kvizer; is_premium: True",
    "1747456805.4394639": "223852270; first_name: Сергей; last_name: None; username: @kvizer; is_premium: True",
    "1747456816.4527435": "223852270; first_name: Сергей; last_name: None; username: @kvizer; is_premium: True",
    "1747456818.5092852": "223852270; first_name: Сергей; last_name: None; username: @kvizer; is_premium: True",
    "1747456819.0849836": "223852270; first_name: Сергей; last_name: None; username: @kvizer; is_premium: True",
    "1747457002.2956526": "223852270; first_name: Сергей; last_name: None; username: @kvizer; is_premium: True",
    "1747457003.4456968": "223852270; first_name: Сергей; last_name: None; username: @kvizer; is_premium: True",
    "1747457004.8117776": "223852270; first_name: Сергей; last_name: None; username: @kvizer; is_premium: True",
    "1747457012.3595033": "363232733; first_name: Lestractum (Владимир); last_name: ¯\\_(ツ)_/¯; username: @Lestractum; is_premium: True",
    "1747457014.1343281": "223852270; first_name: Сергей; last_name: None; username: @kvizer; is_premium: True",
    "1747457031.8658364": "363232733; first_name: Lestractum (Владимир); last_name: ¯\\_(ツ)_/¯; username: @Lestractum; is_premium: True",
    "1747457174.7226238": "49605482; first_name: Maksim; last_name: S; username: @MakSot; is_premium: True",
    "1747457414.8740335": "49605482; first_name: Maksim; last_name: S; username: @MakSot; is_premium: True",
    "1747457426.9700952": "49605482; first_name: Maksim; last_name: S; username: @MakSot; is_premium: True",
    "1747458171.227437": "223852270; first_name: Сергей; last_name: None; username: @kvizer; is_premium: True",
    "1747458176.998843": "223852270; first_name: Сергей; last_name: None; username: @kvizer; is_premium: True",
    "1747458196.4283466": "223852270; first_name: Сергей; last_name: None; username: @kvizer; is_premium: True",
    "1747458197.63469": "223852270; first_name: Сергей; last_name: None; username: @kvizer; is_premium: True",
    "1747458198.598703": "223852270; first_name: Сергей; last_name: None; username: @kvizer; is_premium: True",
    "1747458199.5091288": "223852270; first_name: Сергей; last_name: None; username: @kvizer; is_premium: True",
    "1747458204.9380417": "223852270; first_name: Сергей; last_name: None; username: @kvizer; is_premium: True",
    "1747458217.7669835": "223852270; first_name: Сергей; last_name: None; username: @kvizer; is_premium: True",
    "1747458220.0259182": "223852270; first_name: Сергей; last_name: None; username: @kvizer; is_premium: True",
    "1747458221.410143": "223852270; first_name: Сергей; last_name: None; username: @kvizer; is_premium: True",
    "1747458223.2758105": "223852270; first_name: Сергей; last_name: None; username: @kvizer; is_premium: True",
    "1747458242.8641772": "223852270; first_name: Сергей; last_name: None; username: @kvizer; is_premium: True",
    "1747458451.9490979": "903454809; first_name: 42388; last_name: None; username: @firementat; is_premium: None",
    "1747458455.5399587": "903454809; first_name: 42388; last_name: None; username: @firementat; is_premium: None",
    "1747458457.2928197": "903454809; first_name: 42388; last_name: None; username: @firementat; is_premium: None",
    "1747458463.7647045": "903454809; first_name: 42388; last_name: None; username: @firementat; is_premium: None",
    "1747458467.1620507": "903454809; first_name: 42388; last_name: None; username: @firementat; is_premium: None",
    "1747458480.5169387": "903454809; first_name: 42388; last_name: None; username: @firementat; is_premium: None",
    "1747458483.1106222": "903454809; first_name: 42388; last_name: None; username: @firementat; is_premium: None",
    "1747458842.3148115": "223852270; first_name: Сергей; last_name: None; username: @kvizer; is_premium: True",
    "1747458856.7327702": "223852270; first_name: Сергей; last_name: None; username: @kvizer; is_premium: True",
    "1747458860.611364": "223852270; first_name: Сергей; last_name: None; username: @kvizer; is_premium: True",
    "1747459443.805218": "903454809; first_name: 42388; last_name: None; username: @firementat; is_premium: None",
    "1747459454.007035": "903454809; first_name: 42388; last_name: None; username: @firementat; is_premium: None",
    "1747459510.431968": "903454809; first_name: 42388; last_name: None; username: @firementat; is_premium: None",
    "1747459520.8535755": "903454809; first_name: 42388; last_name: None; username: @firementat; is_premium: None",
    "1747459523.0265613": "903454809; first_name: 42388; last_name: None; username: @firementat; is_premium: None",
    "1747459531.788393": "903454809; first_name: 42388; last_name: None; username: @firementat; is_premium: None",
    "1747459533.4031975": "903454809; first_name: 42388; last_name: None; username: @firementat; is_premium: None",
    "1747459536.2551482": "903454809; first_name: 42388; last_name: None; username: @firementat; is_premium: None",
    "1747459537.8906105": "903454809; first_name: 42388; last_name: None; username: @firementat; is_premium: None",
    "1747459540.0820508": "903454809; first_name: 42388; last_name: None; username: @firementat; is_premium: None",
    "1747459712.568705": "223852270; first_name: Сергей; last_name: None; username: @kvizer; is_premium: True",
    "1747459714.497626": "223852270; first_name: Сергей; last_name: None; username: @kvizer; is_premium: True",
    "1747459725.3082056": "223852270; first_name: Сергей; last_name: None; username: @kvizer; is_premium: True",
    "1747459797.7341135": "223852270; first_name: Сергей; last_name: None; username: @kvizer; is_premium: True",
    "1747460456.8633811": "247001042; first_name: Инна; last_name: С.; username: @inna_smi; is_premium: None",
    "1747460910.0686698": "903454809; first_name: 42388; last_name: None; username: @firementat; is_premium: None",
    "1747460923.9705024": "903454809; first_name: 42388; last_name: None; username: @firementat; is_premium: None",
    "1747460929.825854": "903454809; first_name: 42388; last_name: None; username: @firementat; is_premium: None",
    "1747460933.3430734": "903454809; first_name: 42388; last_name: None; username: @firementat; is_premium: None",
    "1747460939.742208": "903454809; first_name: 42388; last_name: None; username: @firementat; is_premium: None",
    "1747460949.2805178": "903454809; first_name: 42388; last_name: None; username: @firementat; is_premium: None",
    "1747460952.43715": "903454809; first_name: 42388; last_name: None; username: @firementat; is_premium: None",
    "1747460962.2416348": "903454809; first_name: 42388; last_name: None; username: @firementat; is_premium: None",
    "1747460964.2175665": "903454809; first_name: 42388; last_name: None; username: @firementat; is_premium: None",
    "1747460967.2243407": "903454809; first_name: 42388; last_name: None; username: @firementat; is_premium: None",
    "1747460970.8823671": "903454809; first_name: 42388; last_name: None; username: @firementat; is_premium: None",
    "1747460984.2733665": "903454809; first_name: 42388; last_name: None; username: @firementat; is_premium: None",
    "1747460994.7785692": "903454809; first_name: 42388; last_name: None; username: @firementat; is_premium: None",
    "1747460998.1941674": "903454809; first_name: 42388; last_name: None; username: @firementat; is_premium: None",
    "1747461050.5183241": "903454809; first_name: 42388; last_name: None; username: @firementat; is_premium: None",
    "1747461632.953487": "301225274; first_name: Алексей; last_name: Викторович; username: @None; is_premium: None",
    "1747462157.446628": "223852270; first_name: Сергей; last_name: None; username: @kvizer; is_premium: True",
    "1747462166.443482": "223852270; first_name: Сергей; last_name: None; username: @kvizer; is_premium: True",
    "1747462170.2124982": "223852270; first_name: Сергей; last_name: None; username: @kvizer; is_premium: True",
    "1747462183.8494394": "223852270; first_name: Сергей; last_name: None; username: @kvizer; is_premium: True",
    "1747462214.4083757": "223852270; first_name: Сергей; last_name: None; username: @kvizer; is_premium: True",
    "1747462282.2834237": "223852270; first_name: Сергей; last_name: None; username: @kvizer; is_premium: True",
    "1747462491.8575761": "223852270; first_name: Сергей; last_name: None; username: @kvizer; is_premium: True",
    "1747462493.9743216": "223852270; first_name: Сергей; last_name: None; username: @kvizer; is_premium: True",
    "1747462494.6558363": "223852270; first_name: Сергей; last_name: None; username: @kvizer; is_premium: True",
    "1747462496.2094061": "223852270; first_name: Сергей; last_name: None; username: @kvizer; is_premium: True",
    "1747462517.2974398": "223852270; first_name: Сергей; last_name: None; username: @kvizer; is_premium: True",
    "1747462542.0622244": "223852270; first_name: Сергей; last_name: None; username: @kvizer; is_premium: True",
    "1747462544.1161892": "223852270; first_name: Сергей; last_name: None; username: @kvizer; is_premium: True",
    "1747462545.4192944": "223852270; first_name: Сергей; last_name: None; username: @kvizer; is_premium: True",
    "1747462567.701128": "5162857627; first_name: Оля; last_name: Панферова; username: @None; is_premium: None",
    "1747462598.870481": "5162857627; first_name: Оля; last_name: Панферова; username: @None; is_premium: None",
    "1747462691.5308897": "223852270; first_name: Сергей; last_name: None; username: @kvizer; is_premium: True",
    "1747462693.4751685": "223852270; first_name: Сергей; last_name: None; username: @kvizer; is_premium: True",
    "1747462693.560941": "223852270; first_name: Сергей; last_name: None; username: @kvizer; is_premium: True",
    "1747462694.9050417": "223852270; first_name: Сергей; last_name: None; username: @kvizer; is_premium: True",
    "1747462752.4137628": "223852270; first_name: Сергей; last_name: None; username: @kvizer; is_premium: True",
    "1747462774.4026048": "223852270; first_name: Сергей; last_name: None; username: @kvizer; is_premium: True",
    "1747462775.0327997": "448156830; first_name: Григорий; last_name: Панасенко; username: @panasenkogrigory; is_premium: True",
    "1747462779.052448": "223852270; first_name: Сергей; last_name: None; username: @kvizer; is_premium: True",
    "1747462782.9504528": "223852270; first_name: Сергей; last_name: None; username: @kvizer; is_premium: True",
    "1747462785.862759": "223852270; first_name: Сергей; last_name: None; username: @kvizer; is_premium: True",
    "1747462787.6171818": "223852270; first_name: Сергей; last_name: None; username: @kvizer; is_premium: True",
    "1747462938.76284": "448156830; first_name: Григорий; last_name: Панасенко; username: @panasenkogrigory; is_premium: True",
    "1747463650.5579307": "372951864; first_name: Mарина; last_name: Яхонтова; username: @notes_of_young_psy; is_premium: True",
    "1747463711.7175353": "223852270; first_name: Сергей; last_name: None; username: @kvizer; is_premium: True",
    "1747463735.6637607": "223852270; first_name: Сергей; last_name: None; username: @kvizer; is_premium: True",
    "1747463744.1847944": "223852270; first_name: Сергей; last_name: None; username: @kvizer; is_premium: True",
    "1747464913.6845846": "448156830; first_name: Григорий; last_name: Панасенко; username: @panasenkogrigory; is_premium: True",
    "1747464936.6022944": "796320373; first_name: Юлия Евстратова; last_name: None; username: @None; is_premium: None",
    "1747464989.165243": "796320373; first_name: Юлия Евстратова; last_name: None; username: @None; is_premium: None",
    "1747464994.369906": "796320373; first_name: Юлия Евстратова; last_name: None; username: @None; is_premium: None",
    "1747465014.1705873": "796320373; first_name: Юлия Евстратова; last_name: None; username: @None; is_premium: None",
    "1747465154.6124322": "448156830; first_name: Григорий; last_name: Панасенко; username: @panasenkogrigory; is_premium: True",
    "1747465644.131108": "223852270; first_name: Сергей; last_name: None; username: @kvizer; is_premium: True",
    "1747465647.502172": "223852270; first_name: Сергей; last_name: None; username: @kvizer; is_premium: True",
    "1747465648.6773653": "223852270; first_name: Сергей; last_name: None; username: @kvizer; is_premium: True",
    "1747465650.2051044": "223852270; first_name: Сергей; last_name: None; username: @kvizer; is_premium: True",
    "1747465651.2914045": "223852270; first_name: Сергей; last_name: None; username: @kvizer; is_premium: True",
    "1747465652.2467875": "223852270; first_name: Сергей; last_name: None; username: @kvizer; is_premium: True",
    "1747466416.9051232": "680083358; first_name: paranoidtiltedbipolar; last_name: None; username: @qpoizon; is_premium: None",
    "1747466435.6024566": "680083358; first_name: paranoidtiltedbipolar; last_name: None; username: @qpoizon; is_premium: None",
    "1747467171.9192283": "223852270; first_name: Сергей; last_name: None; username: @kvizer; is_premium: True",
    "1747467190.1114004": "223852270; first_name: Сергей; last_name: None; username: @kvizer; is_premium: True",
    "1747467203.5825012": "223852270; first_name: Сергей; last_name: None; username: @kvizer; is_premium: True",
    "1747467213.6372743": "223852270; first_name: Сергей; last_name: None; username: @kvizer; is_premium: True",
    "1747467216.6825454": "223852270; first_name: Сергей; last_name: None; username: @kvizer; is_premium: True",
    "1747467220.2561283": "223852270; first_name: Сергей; last_name: None; username: @kvizer; is_premium: True",
    "1747467246.685414": "223852270; first_name: Сергей; last_name: None; username: @kvizer; is_premium: True",
    "1747467260.0689518": "223852270; first_name: Сергей; last_name: None; username: @kvizer; is_premium: True",
    "1747467264.0673964": "223852270; first_name: Сергей; last_name: None; username: @kvizer; is_premium: True",
    "1747467280.0646496": "223852270; first_name: Сергей; last_name: None; username: @kvizer; is_premium: True",
    "1747468905.039863": "762352339; first_name: Eery; last_name: None; username: @Eery365; is_premium: True",
    "1747469385.0709555": "223852270; first_name: Сергей; last_name: None; username: @kvizer; is_premium: True",
    "1747469416.3825057": "223852270; first_name: Сергей; last_name: None; username: @kvizer; is_premium: True",
    "1747469467.0181844": "223852270; first_name: Сергей; last_name: None; username: @kvizer; is_premium: True",
    "1747469470.091375": "223852270; first_name: Сергей; last_name: None; username: @kvizer; is_premium: True",
    "1747469483.328219": "223852270; first_name: Сергей; last_name: None; username: @kvizer; is_premium: True",
    "1747469650.559658": "223852270; first_name: Сергей; last_name: None; username: @kvizer; is_premium: True",
    "1747469682.0986855": "223852270; first_name: Сергей; last_name: None; username: @kvizer; is_premium: True",
    "1747469689.6781132": "223852270; first_name: Сергей; last_name: None; username: @kvizer; is_premium: True",
    "1747469693.69214": "223852270; first_name: Сергей; last_name: None; username: @kvizer; is_premium: True",
    "1747469697.2949233": "223852270; first_name: Сергей; last_name: None; username: @kvizer; is_premium: True",
    "1747469705.1520839": "223852270; first_name: Сергей; last_name: None; username: @kvizer; is_premium: True",
    "1747469982.1194248": "697124089; first_name: Vincent; last_name: None; username: @sgorbatenko; is_premium: None",
    "1747472888.3642101": "223852270; first_name: Сергей; last_name: None; username: @kvizer; is_premium: True",
    "1747472893.3590393": "223852270; first_name: Сергей; last_name: None; username: @kvizer; is_premium: True",
    "1747480864.163747": "223852270; first_name: Сергей; last_name: None; username: @kvizer; is_premium: True",
    "1747480874.2364619": "223852270; first_name: Сергей; last_name: None; username: @kvizer; is_premium: True",
    "1747480875.6530335": "223852270; first_name: Сергей; last_name: None; username: @kvizer; is_premium: True",
    "1747480876.457486": "223852270; first_name: Сергей; last_name: None; username: @kvizer; is_premium: True",
    "1747480879.847751": "223852270; first_name: Сергей; last_name: None; username: @kvizer; is_premium: True",
    "1747481056.3231833": "223852270; first_name: Сергей; last_name: None; username: @kvizer; is_premium: True",
    "1747481078.289357": "223852270; first_name: Сергей; last_name: None; username: @kvizer; is_premium: True",
    "1747481089.5843143": "223852270; first_name: Сергей; last_name: None; username: @kvizer; is_premium: True",
    "1747481156.416245": "223852270; first_name: Сергей; last_name: None; username: @kvizer; is_premium: True",
    "1747481164.5365794": "223852270; first_name: Сергей; last_name: None; username: @kvizer; is_premium: True",
    "1747481195.6548676": "223852270; first_name: Сергей; last_name: None; username: @kvizer; is_premium: True",
    "1747481217.4737632": "223852270; first_name: Сергей; last_name: None; username: @kvizer; is_premium: True",
    "1747481331.9170551": "223852270; first_name: Сергей; last_name: None; username: @kvizer; is_premium: True",
    "1747481334.2499607": "223852270; first_name: Сергей; last_name: None; username: @kvizer; is_premium: True",
    "1747481336.0653882": "223852270; first_name: Сергей; last_name: None; username: @kvizer; is_premium: True",
    "1747481338.392683": "223852270; first_name: Сергей; last_name: None; username: @kvizer; is_premium: True",
    "1747481341.4250333": "223852270; first_name: Сергей; last_name: None; username: @kvizer; is_premium: True",
    "1747481344.751128": "223852270; first_name: Сергей; last_name: None; username: @kvizer; is_premium: True",
    "1747481347.4274678": "223852270; first_name: Сергей; last_name: None; username: @kvizer; is_premium: True",
    "1747481349.604121": "223852270; first_name: Сергей; last_name: None; username: @kvizer; is_premium: True",
    "1747481351.5901432": "223852270; first_name: Сергей; last_name: None; username: @kvizer; is_premium: True",
    "1747481354.145833": "223852270; first_name: Сергей; last_name: None; username: @kvizer; is_premium: True",
    "1747481357.0937562": "223852270; first_name: Сергей; last_name: None; username: @kvizer; is_premium: True",
    "1747481360.0726879": "223852270; first_name: Сергей; last_name: None; username: @kvizer; is_premium: True",
    "1747481362.904531": "223852270; first_name: Сергей; last_name: None; username: @kvizer; is_premium: True",
    "1747481365.1303058": "223852270; first_name: Сергей; last_name: None; username: @kvizer; is_premium: True",
    "1747481367.80663": "223852270; first_name: Сергей; last_name: None; username: @kvizer; is_premium: True",
    "1747481370.610643": "223852270; first_name: Сергей; last_name: None; username: @kvizer; is_premium: True",
    "1747481372.9808967": "223852270; first_name: Сергей; last_name: None; username: @kvizer; is_premium: True",
    "1747481392.5699182": "223852270; first_name: Сергей; last_name: None; username: @kvizer; is_premium: True",
    "1747481404.8357868": "223852270; first_name: Сергей; last_name: None; username: @kvizer; is_premium: True",
    "1747481409.3218205": "223852270; first_name: Сергей; last_name: None; username: @kvizer; is_premium: True",
    "1747481410.3934267": "223852270; first_name: Сергей; last_name: None; username: @kvizer; is_premium: True",
    "1747481531.966305": "223852270; first_name: Сергей; last_name: None; username: @kvizer; is_premium: True",
    "1747481554.6653225": "223852270; first_name: Сергей; last_name: None; username: @kvizer; is_premium: True",
    "1747481558.7774918": "223852270; first_name: Сергей; last_name: None; username: @kvizer; is_premium: True",
    "1747481560.933846": "223852270; first_name: Сергей; last_name: None; username: @kvizer; is_premium: True",
    "1747481563.3960185": "223852270; first_name: Сергей; last_name: None; username: @kvizer; is_premium: True",
    "1747481565.678876": "223852270; first_name: Сергей; last_name: None; username: @kvizer; is_premium: True",
    "1747481569.373566": "223852270; first_name: Сергей; last_name: None; username: @kvizer; is_premium: True",
    "1747481572.4129162": "223852270; first_name: Сергей; last_name: None; username: @kvizer; is_premium: True",
    "1747481575.150505": "223852270; first_name: Сергей; last_name: None; username: @kvizer; is_premium: True",
    "1747481578.1457248": "223852270; first_name: Сергей; last_name: None; username: @kvizer; is_premium: True",
    "1747481580.452109": "223852270; first_name: Сергей; last_name: None; username: @kvizer; is_premium: True",
    "1747481583.1861815": "223852270; first_name: Сергей; last_name: None; username: @kvizer; is_premium: True",
    "1747481590.6608": "223852270; first_name: Сергей; last_name: None; username: @kvizer; is_premium: True",
    "1747481629.5842628": "223852270; first_name: Сергей; last_name: None; username: @kvizer; is_premium: True",
    "1747481631.349288": "223852270; first_name: Сергей; last_name: None; username: @kvizer; is_premium: True",
    "1747481633.7758772": "223852270; first_name: Сергей; last_name: None; username: @kvizer; is_premium: True",
    "1747481636.8786516": "223852270; first_name: Сергей; last_name: None; username: @kvizer; is_premium: True",
    "1747481640.0817428": "223852270; first_name: Сергей; last_name: None; username: @kvizer; is_premium: True",
    "1747481644.5989952": "223852270; first_name: Сергей; last_name: None; username: @kvizer; is_premium: True",
    "1747481646.537976": "448156830; first_name: Григорий; last_name: Панасенко; username: @panasenkogrigory; is_premium: True",
    "1747481646.6972482": "223852270; first_name: Сергей; last_name: None; username: @kvizer; is_premium: True",
    "1747481646.827825": "223852270; first_name: Сергей; last_name: None; username: @kvizer; is_premium: True",
    "1747481650.5472322": "223852270; first_name: Сергей; last_name: None; username: @kvizer; is_premium: True",
    "1747481667.8164167": "448156830; first_name: Григорий; last_name: Панасенко; username: @panasenkogrigory; is_premium: True",
    "1747481671.2445602": "223852270; first_name: Сергей; last_name: None; username: @kvizer; is_premium: True",
    "1747481672.4385693": "223852270; first_name: Сергей; last_name: None; username: @kvizer; is_premium: True",
    "1747481970.8967865": "363232733; first_name: Lestractum (Владимир); last_name: ¯\\_(ツ)_/¯; username: @Lestractum; is_premium: True",
    "1747481992.4773064": "363232733; first_name: Lestractum (Владимир); last_name: ¯\\_(ツ)_/¯; username: @Lestractum; is_premium: True",
    "1747482001.4318745": "363232733; first_name: Lestractum (Владимир); last_name: ¯\\_(ツ)_/¯; username: @Lestractum; is_premium: True",
    "1747482048.6797845": "5162857627; first_name: Оля; last_name: Панферова; username: @None; is_premium: None",
    "1747482078.4803336": "5162857627; first_name: Оля; last_name: Панферова; username: @None; is_premium: None",
    "1747482157.1457582": "903454809; first_name: 42388; last_name: None; username: @firementat; is_premium: None",
    "1747482203.6234915": "903454809; first_name: 42388; last_name: None; username: @firementat; is_premium: None",
    "1747482363.466537": "5162857627; first_name: Оля; last_name: Панферова; username: @None; is_premium: None",
    "1747482638.5792437": "903454809; first_name: 42388; last_name: None; username: @firementat; is_premium: None",
    "1747482641.1511042": "903454809; first_name: 42388; last_name: None; username: @firementat; is_premium: None",
    "1747482662.467963": "903454809; first_name: 42388; last_name: None; username: @firementat; is_premium: None",
    "1747482683.8045177": "903454809; first_name: 42388; last_name: None; username: @firementat; is_premium: None",
    "1747482770.613799": "903454809; first_name: 42388; last_name: None; username: @firementat; is_premium: None",
    "1747482817.6850915": "223852270; first_name: Сергей; last_name: None; username: @kvizer; is_premium: True",
    "1747482820.2576597": "903454809; first_name: 42388; last_name: None; username: @firementat; is_premium: None",
    "1747482831.034951": "903454809; first_name: 42388; last_name: None; username: @firementat; is_premium: None",
    "1747482832.6430316": "903454809; first_name: 42388; last_name: None; username: @firementat; is_premium: None",
    "1747483007.6453574": "903454809; first_name: 42388; last_name: None; username: @firementat; is_premium: None",
    "1747483016.0756626": "903454809; first_name: 42388; last_name: None; username: @firementat; is_premium: None",
    "1747483175.8648584": "223852270; first_name: Сергей; last_name: None; username: @kvizer; is_premium: True",
    "1747483189.7390597": "223852270; first_name: Сергей; last_name: None; username: @kvizer; is_premium: True",
    "1747483195.9857237": "223852270; first_name: Сергей; last_name: None; username: @kvizer; is_premium: True",
    "1747483201.1448956": "223852270; first_name: Сергей; last_name: None; username: @kvizer; is_premium: True",
    "1747483212.3195498": "223852270; first_name: Сергей; last_name: None; username: @kvizer; is_premium: True",
    "1747483217.9265604": "223852270; first_name: Сергей; last_name: None; username: @kvizer; is_premium: True",
    "1747483226.0683937": "223852270; first_name: Сергей; last_name: None; username: @kvizer; is_premium: True",
    "1747483229.7499504": "223852270; first_name: Сергей; last_name: None; username: @kvizer; is_premium: True",
    "1747483232.1799095": "223852270; first_name: Сергей; last_name: None; username: @kvizer; is_premium: True",
    "1747483234.2421274": "223852270; first_name: Сергей; last_name: None; username: @kvizer; is_premium: True",
    "1747483286.1307547": "223852270; first_name: Сергей; last_name: None; username: @kvizer; is_premium: True",
    "1747483327.629836": "796320373; first_name: Юлия Евстратова; last_name: None; username: @None; is_premium: None",
    "1747483385.207812": "223852270; first_name: Сергей; last_name: None; username: @kvizer; is_premium: True",
    "1747483387.0919929": "223852270; first_name: Сергей; last_name: None; username: @kvizer; is_premium: True",
    "1747483387.7630942": "223852270; first_name: Сергей; last_name: None; username: @kvizer; is_premium: True",
    "1747483388.4423442": "223852270; first_name: Сергей; last_name: None; username: @kvizer; is_premium: True",
    "1747483392.4678175": "223852270; first_name: Сергей; last_name: None; username: @kvizer; is_premium: True",
    "1747483395.3595076": "223852270; first_name: Сергей; last_name: None; username: @kvizer; is_premium: True",
    "1747483397.526539": "223852270; first_name: Сергей; last_name: None; username: @kvizer; is_premium: True",
    "1747483401.56851": "223852270; first_name: Сергей; last_name: None; username: @kvizer; is_premium: True",
    "1747483403.849661": "223852270; first_name: Сергей; last_name: None; username: @kvizer; is_premium: True",
    "1747483406.954706": "223852270; first_name: Сергей; last_name: None; username: @kvizer; is_premium: True",
    "1747483410.0282063": "223852270; first_name: Сергей; last_name: None; username: @kvizer; is_premium: True",
    "1747483413.4982612": "223852270; first_name: Сергей; last_name: None; username: @kvizer; is_premium: True",
    "1747483417.7267761": "223852270; first_name: Сергей; last_name: None; username: @kvizer; is_premium: True",
    "1747483606.4617388": "223852270; first_name: Сергей; last_name: None; username: @kvizer; is_premium: True",
    "1747483630.0083652": "223852270; first_name: Сергей; last_name: None; username: @kvizer; is_premium: True",
    "1747483644.1539776": "223852270; first_name: Сергей; last_name: None; username: @kvizer; is_premium: True",
    "1747483648.363245": "223852270; first_name: Сергей; last_name: None; username: @kvizer; is_premium: True",
    "1747483650.4666407": "223852270; first_name: Сергей; last_name: None; username: @kvizer; is_premium: True",
    "1747483652.4394395": "223852270; first_name: Сергей; last_name: None; username: @kvizer; is_premium: True",
    "1747483654.6174538": "223852270; first_name: Сергей; last_name: None; username: @kvizer; is_premium: True",
    "1747483658.803832": "223852270; first_name: Сергей; last_name: None; username: @kvizer; is_premium: True",
    "1747483661.2363524": "223852270; first_name: Сергей; last_name: None; username: @kvizer; is_premium: True",
    "1747483663.7844365": "223852270; first_name: Сергей; last_name: None; username: @kvizer; is_premium: True",
    "1747483712.6652515": "223852270; first_name: Сергей; last_name: None; username: @kvizer; is_premium: True",
    "1747483812.2588968": "680083358; first_name: paranoidtiltedbipolar; last_name: None; username: @qpoizon; is_premium: None",
    "1747483829.480825": "680083358; first_name: paranoidtiltedbipolar; last_name: None; username: @qpoizon; is_premium: None",
    "1747483852.9781635": "680083358; first_name: paranoidtiltedbipolar; last_name: None; username: @qpoizon; is_premium: None",
    "1747483955.8301995": "796320373; first_name: Юлия Евстратова; last_name: None; username: @None; is_premium: None",
    "1747484511.2114646": "223852270; first_name: Сергей; last_name: None; username: @kvizer; is_premium: True",
    "1747484535.8069468": "223852270; first_name: Сергей; last_name: None; username: @kvizer; is_premium: True",
    "1747484541.2629254": "223852270; first_name: Сергей; last_name: None; username: @kvizer; is_premium: True",
    "1747484546.3352559": "223852270; first_name: Сергей; last_name: None; username: @kvizer; is_premium: True",
    "1747484549.5083804": "223852270; first_name: Сергей; last_name: None; username: @kvizer; is_premium: True",
    "1747485323.1491883": "223852270; first_name: Сергей; last_name: None; username: @kvizer; is_premium: True",
    "1747485344.6548803": "223852270; first_name: Сергей; last_name: None; username: @kvizer; is_premium: True",
    "1747485348.645635": "223852270; first_name: Сергей; last_name: None; username: @kvizer; is_premium: True",
    "1747485352.3259916": "223852270; first_name: Сергей; last_name: None; username: @kvizer; is_premium: True",
    "1747485354.5391293": "223852270; first_name: Сергей; last_name: None; username: @kvizer; is_premium: True",
    "1747485359.9342136": "223852270; first_name: Сергей; last_name: None; username: @kvizer; is_premium: True",
    "1747485362.404456": "223852270; first_name: Сергей; last_name: None; username: @kvizer; is_premium: True",
    "1747485364.4331129": "223852270; first_name: Сергей; last_name: None; username: @kvizer; is_premium: True",
    "1747485366.296337": "223852270; first_name: Сергей; last_name: None; username: @kvizer; is_premium: True",
    "1747485368.987828": "223852270; first_name: Сергей; last_name: None; username: @kvizer; is_premium: True",
    "1747485370.9086294": "223852270; first_name: Сергей; last_name: None; username: @kvizer; is_premium: True",
    "1747485375.5408347": "223852270; first_name: Сергей; last_name: None; username: @kvizer; is_premium: True",
    "1747485385.7110033": "223852270; first_name: Сергей; last_name: None; username: @kvizer; is_premium: True",
    "1747485386.7137077": "223852270; first_name: Сергей; last_name: None; username: @kvizer; is_premium: True",
    "1747485387.4604998": "223852270; first_name: Сергей; last_name: None; username: @kvizer; is_premium: True",
    "1747485387.9478958": "223852270; first_name: Сергей; last_name: None; username: @kvizer; is_premium: True",
    "1747485388.301314": "223852270; first_name: Сергей; last_name: None; username: @kvizer; is_premium: True",
    "1747485388.4641507": "223852270; first_name: Сергей; last_name: None; username: @kvizer; is_premium: True",
    "1747487189.2345617": "223852270; first_name: Сергей; last_name: None; username: @kvizer; is_premium: True",
    "1747487775.8789227": "49605482; first_name: Maksim; last_name: S; username: @MakSot; is_premium: True",
    "1747487785.826856": "49605482; first_name: Maksim; last_name: S; username: @MakSot; is_premium: True",
    "1747489736.9454412": "223852270; first_name: Сергей; last_name: None; username: @kvizer; is_premium: True",
    "1747489752.6140246": "223852270; first_name: Сергей; last_name: None; username: @kvizer; is_premium: True",
    "1747489759.0059671": "223852270; first_name: Сергей; last_name: None; username: @kvizer; is_premium: True",
    "1747492160.6038609": "223852270; first_name: Сергей; last_name: None; username: @kvizer; is_premium: True",
    "1747492174.918519": "223852270; first_name: Сергей; last_name: None; username: @kvizer; is_premium: True",
    "1747496148.4364395": "223852270; first_name: Сергей; last_name: None; username: @kvizer; is_premium: True",
    "1747496167.190363": "223852270; first_name: Сергей; last_name: None; username: @kvizer; is_premium: True",
    "1747496170.485288": "223852270; first_name: Сергей; last_name: None; username: @kvizer; is_premium: True",
    "1747496173.205892": "223852270; first_name: Сергей; last_name: None; username: @kvizer; is_premium: True",
    "1747496176.3218648": "223852270; first_name: Сергей; last_name: None; username: @kvizer; is_premium: True",
    "1747496178.3826315": "223852270; first_name: Сергей; last_name: None; username: @kvizer; is_premium: True",
    "1747496179.9705048": "223852270; first_name: Сергей; last_name: None; username: @kvizer; is_premium: True",
    "1747496182.6149676": "223852270; first_name: Сергей; last_name: None; username: @kvizer; is_premium: True",
    "1747496184.7089632": "223852270; first_name: Сергей; last_name: None; username: @kvizer; is_premium: True",
    "1747496186.985738": "223852270; first_name: Сергей; last_name: None; username: @kvizer; is_premium: True",
    "1747496188.1887243": "223852270; first_name: Сергей; last_name: None; username: @kvizer; is_premium: True",
    "1747496190.4951243": "223852270; first_name: Сергей; last_name: None; username: @kvizer; is_premium: True",
    "1747496191.522676": "223852270; first_name: Сергей; last_name: None; username: @kvizer; is_premium: True",
    "1747500154.610614": "223852270; first_name: Сергей; last_name: None; username: @kvizer; is_premium: True",
    "1747502022.1796203": "223852270; first_name: Сергей; last_name: None; username: @kvizer; is_premium: True",
    "1747502056.3019469": "223852270; first_name: Сергей; last_name: None; username: @kvizer; is_premium: True",
    "1747502062.421445": "223852270; first_name: Сергей; last_name: None; username: @kvizer; is_premium: True",
    "1747502066.0484116": "223852270; first_name: Сергей; last_name: None; username: @kvizer; is_premium: True",
    "1747502071.0036306": "223852270; first_name: Сергей; last_name: None; username: @kvizer; is_premium: True",
    "1747502077.2224467": "223852270; first_name: Сергей; last_name: None; username: @kvizer; is_premium: True",
    "1747502082.0613515": "223852270; first_name: Сергей; last_name: None; username: @kvizer; is_premium: True",
    "1747502086.1012702": "223852270; first_name: Сергей; last_name: None; username: @kvizer; is_premium: True",
    "1747502091.9324863": "223852270; first_name: Сергей; last_name: None; username: @kvizer; is_premium: True",
    "1747502127.0070686": "223852270; first_name: Сергей; last_name: None; username: @kvizer; is_premium: True",
    "1747515124.7109756": "697124089; first_name: Vincent; last_name: None; username: @sgorbatenko; is_premium: None",
    "1747515136.1552594": "697124089; first_name: Vincent; last_name: None; username: @sgorbatenko; is_premium: None"
}