{
    "1747602682.5796785": "223852270; first_name: Сергей; last_name: None; username: @kvizer; is_premium: True",
    "1747602762.167491": "223852270; first_name: Сергей; last_name: None; username: @kvizer; is_premium: True",
    "1747602767.9385505": "223852270; first_name: Сергей; last_name: None; username: @kvizer; is_premium: True",
    "1747602775.8462224": "223852270; first_name: Сергей; last_name: None; username: @kvizer; is_premium: True",
    "1747602787.742149": "223852270; first_name: Сергей; last_name: None; username: @kvizer; is_premium: True",
    "1747602796.746164": "223852270; first_name: Сергей; last_name: None; username: @kvizer; is_premium: True",
    "1747603072.7689812": "223852270; first_name: Сергей; last_name: None; username: @kvizer; is_premium: True",
    "1747605427.1157959": "223852270; first_name: Сергей; last_name: None; username: @kvizer; is_premium: True",
    "1747605457.578608": "223852270; first_name: Сергей; last_name: None; username: @kvizer; is_premium: True",
    "1747605473.0579414": "223852270; first_name: Сергей; last_name: None; username: @kvizer; is_premium: True",
    "1747605482.760393": "223852270; first_name: Сергей; last_name: None; username: @kvizer; is_premium: True",
    "1747605522.595323": "223852270; first_name: Сергей; last_name: None; username: @kvizer; is_premium: True",
    "1747605562.4682512": "223852270; first_name: Сергей; last_name: None; username: @kvizer; is_premium: True",
    "1747605569.9927728": "223852270; first_name: Сергей; last_name: None; username: @kvizer; is_premium: True",
    "1747605571.6125212": "223852270; first_name: Сергей; last_name: None; username: @kvizer; is_premium: True",
    "1747605573.1803293": "223852270; first_name: Сергей; last_name: None; username: @kvizer; is_premium: True",
    "1747605574.9251938": "223852270; first_name: Сергей; last_name: None; username: @kvizer; is_premium: True",
    "1747605577.076442": "223852270; first_name: Сергей; last_name: None; username: @kvizer; is_premium: True",
    "1747605579.1505675": "223852270; first_name: Сергей; last_name: None; username: @kvizer; is_premium: True",
    "1747605582.9055817": "223852270; first_name: Сергей; last_name: None; username: @kvizer; is_premium: True",
    "1747605599.243408": "223852270; first_name: Сергей; last_name: None; username: @kvizer; is_premium: True",
    "1747605602.7005773": "223852270; first_name: Сергей; last_name: None; username: @kvizer; is_premium: True",
    "1747605603.7959774": "223852270; first_name: Сергей; last_name: None; username: @kvizer; is_premium: True",
    "1747605605.0299184": "223852270; first_name: Сергей; last_name: None; username: @kvizer; is_premium: True",
    "1747605605.984847": "223852270; first_name: Сергей; last_name: None; username: @kvizer; is_premium: True",
    "1747605607.9904253": "223852270; first_name: Сергей; last_name: None; username: @kvizer; is_premium: True",
    "1747605609.105371": "223852270; first_name: Сергей; last_name: None; username: @kvizer; is_premium: True",
    "1747605661.8176687": "223852270; first_name: Сергей; last_name: None; username: @kvizer; is_premium: True",
    "1747605668.9622679": "223852270; first_name: Сергей; last_name: None; username: @kvizer; is_premium: True",
    "1747605670.749135": "223852270; first_name: Сергей; last_name: None; username: @kvizer; is_premium: True",
    "1747605704.808013": "223852270; first_name: Сергей; last_name: None; username: @kvizer; is_premium: True",
    "1747605714.3078158": "223852270; first_name: Сергей; last_name: None; username: @kvizer; is_premium: True",
    "1747605717.7888043": "223852270; first_name: Сергей; last_name: None; username: @kvizer; is_premium: True",
    "1747605721.1546903": "223852270; first_name: Сергей; last_name: None; username: @kvizer; is_premium: True",
    "1747605724.1097791": "223852270; first_name: Сергей; last_name: None; username: @kvizer; is_premium: True",
    "1747605726.8869": "223852270; first_name: Сергей; last_name: None; username: @kvizer; is_premium: True",
    "1747605729.6351085": "223852270; first_name: Сергей; last_name: None; username: @kvizer; is_premium: True",
    "1747605733.3115172": "223852270; first_name: Сергей; last_name: None; username: @kvizer; is_premium: True",
    "1747605756.4607024": "223852270; first_name: Сергей; last_name: None; username: @kvizer; is_premium: True",
    "1747605760.6358514": "223852270; first_name: Сергей; last_name: None; username: @kvizer; is_premium: True",
    "1747605762.3237734": "223852270; first_name: Сергей; last_name: None; username: @kvizer; is_premium: True",
    "1747605764.068818": "223852270; first_name: Сергей; last_name: None; username: @kvizer; is_premium: True",
    "1747605765.9897141": "223852270; first_name: Сергей; last_name: None; username: @kvizer; is_premium: True",
    "1747605768.1818993": "223852270; first_name: Сергей; last_name: None; username: @kvizer; is_premium: True",
    "1747605773.9189358": "223852270; first_name: Сергей; last_name: None; username: @kvizer; is_premium: True",
    "1747605777.0075088": "223852270; first_name: Сергей; last_name: None; username: @kvizer; is_premium: True",
    "1747605780.145885": "223852270; first_name: Сергей; last_name: None; username: @kvizer; is_premium: True",
    "1747605783.8104115": "223852270; first_name: Сергей; last_name: None; username: @kvizer; is_premium: True",
    "1747605801.5579333": "223852270; first_name: Сергей; last_name: None; username: @kvizer; is_premium: True",
    "1747605806.7712595": "223852270; first_name: Сергей; last_name: None; username: @kvizer; is_premium: True",
    "1747605820.6166923": "223852270; first_name: Сергей; last_name: None; username: @kvizer; is_premium: True",
    "1747605848.0765948": "223852270; first_name: Сергей; last_name: None; username: @kvizer; is_premium: True",
    "1747605869.042668": "223852270; first_name: Сергей; last_name: None; username: @kvizer; is_premium: True",
    "1747605875.9666722": "223852270; first_name: Сергей; last_name: None; username: @kvizer; is_premium: True",
    "1747605883.7784822": "223852270; first_name: Сергей; last_name: None; username: @kvizer; is_premium: True",
    "1747605907.409288": "223852270; first_name: Сергей; last_name: None; username: @kvizer; is_premium: True",
    "1747605917.563511": "223852270; first_name: Сергей; last_name: None; username: @kvizer; is_premium: True",
    "1747605941.3460796": "223852270; first_name: Сергей; last_name: None; username: @kvizer; is_premium: True",
    "1747605948.4323175": "223852270; first_name: Сергей; last_name: None; username: @kvizer; is_premium: True",
    "1747605952.4450958": "223852270; first_name: Сергей; last_name: None; username: @kvizer; is_premium: True",
    "1747605963.4907217": "223852270; first_name: Сергей; last_name: None; username: @kvizer; is_premium: True",
    "1747605967.4995": "223852270; first_name: Сергей; last_name: None; username: @kvizer; is_premium: True",
    "1747605970.7847373": "223852270; first_name: Сергей; last_name: None; username: @kvizer; is_premium: True",
    "1747617764.953725": "5070844382; first_name: Сергей; last_name: None; username: @None; is_premium: None",
    "1747633070.658934": "448156830; first_name: Григорий; last_name: Панасенко; username: @panasenkogrigory; is_premium: True",
    "1747633101.639703": "448156830; first_name: Григорий; last_name: Панасенко; username: @panasenkogrigory; is_premium: True",
    "1747633140.4336858": "448156830; first_name: Григорий; last_name: Панасенко; username: @panasenkogrigory; is_premium: True",
    "1747634316.0319698": "223852270; first_name: Сергей; last_name: None; username: @kvizer; is_premium: True",
    "1747635611.70993": "223852270; first_name: Сергей; last_name: None; username: @kvizer; is_premium: True",
    "1747635624.7002952": "223852270; first_name: Сергей; last_name: None; username: @kvizer; is_premium: True",
    "1747635628.345529": "223852270; first_name: Сергей; last_name: None; username: @kvizer; is_premium: True",
    "1747635648.5369158": "223852270; first_name: Сергей; last_name: None; username: @kvizer; is_premium: True",
    "1747635807.6221943": "223852270; first_name: Сергей; last_name: None; username: @kvizer; is_premium: True",
    "1747636083.114963": "223852270; first_name: Сергей; last_name: None; username: @kvizer; is_premium: True",
    "1747636088.0703766": "223852270; first_name: Сергей; last_name: None; username: @kvizer; is_premium: True",
    "1747636090.1014473": "223852270; first_name: Сергей; last_name: None; username: @kvizer; is_premium: True",
    "1747637208.233219": "223852270; first_name: Сергей; last_name: None; username: @kvizer; is_premium: True",
    "1747637219.4961035": "223852270; first_name: Сергей; last_name: None; username: @kvizer; is_premium: True",
    "1747637223.0775936": "223852270; first_name: Сергей; last_name: None; username: @kvizer; is_premium: True",
    "1747637226.2834165": "223852270; first_name: Сергей; last_name: None; username: @kvizer; is_premium: True",
    "1747637401.8388352": "223852270; first_name: Сергей; last_name: None; username: @kvizer; is_premium: True",
    "1747637447.2562995": "223852270; first_name: Сергей; last_name: None; username: @kvizer; is_premium: True",
    "1747638747.6627889": "223852270; first_name: Сергей; last_name: None; username: @kvizer; is_premium: True",
    "1747638965.0591586": "223852270; first_name: Сергей; last_name: None; username: @kvizer; is_premium: True",
    "1747638991.4567165": "223852270; first_name: Сергей; last_name: None; username: @kvizer; is_premium: True",
    "1747639437.9142556": "223852270; first_name: Сергей; last_name: None; username: @kvizer; is_premium: True",
    "1747639451.4491262": "223852270; first_name: Сергей; last_name: None; username: @kvizer; is_premium: True",
    "1747639475.1420522": "223852270; first_name: Сергей; last_name: None; username: @kvizer; is_premium: True",
    "1747639478.9218647": "223852270; first_name: Сергей; last_name: None; username: @kvizer; is_premium: True",
    "1747639735.999549": "223852270; first_name: Сергей; last_name: None; username: @kvizer; is_premium: True",
    "1747639738.395784": "223852270; first_name: Сергей; last_name: None; username: @kvizer; is_premium: True",
    "1747641479.7673435": "680083358; first_name: paranoidtiltedbipolar; last_name: None; username: @qpoizon; is_premium: None",
    "1747641498.3490477": "680083358; first_name: paranoidtiltedbipolar; last_name: None; username: @qpoizon; is_premium: None",
    "1747641507.3414652": "680083358; first_name: paranoidtiltedbipolar; last_name: None; username: @qpoizon; is_premium: None",
    "1747643290.4464207": "223852270; first_name: Сергей; last_name: None; username: @kvizer; is_premium: True",
    "1747643296.2345395": "223852270; first_name: Сергей; last_name: None; username: @kvizer; is_premium: True",
    "1747643296.4071555": "223852270; first_name: Сергей; last_name: None; username: @kvizer; is_premium: True",
    "1747643586.3767724": "223852270; first_name: Сергей; last_name: None; username: @kvizer; is_premium: True",
    "1747643588.974906": "223852270; first_name: Сергей; last_name: None; username: @kvizer; is_premium: True",
    "1747645234.4990323": "223852270; first_name: Сергей; last_name: None; username: @kvizer; is_premium: True",
    "1747645245.2487335": "223852270; first_name: Сергей; last_name: None; username: @kvizer; is_premium: True",
    "1747645393.9453177": "223852270; first_name: Сергей; last_name: None; username: @kvizer; is_premium: True",
    "1747645412.8541982": "223852270; first_name: Сергей; last_name: None; username: @kvizer; is_premium: True",
    "1747645436.2061357": "223852270; first_name: Сергей; last_name: None; username: @kvizer; is_premium: True",
    "1747645448.7479677": "223852270; first_name: Сергей; last_name: None; username: @kvizer; is_premium: True",
    "1747645459.3873644": "223852270; first_name: Сергей; last_name: None; username: @kvizer; is_premium: True",
    "1747645462.3074505": "223852270; first_name: Сергей; last_name: None; username: @kvizer; is_premium: True",
    "1747645469.0242763": "223852270; first_name: Сергей; last_name: None; username: @kvizer; is_premium: True",
    "1747645492.6391556": "223852270; first_name: Сергей; last_name: None; username: @kvizer; is_premium: True",
    "1747645501.7391002": "223852270; first_name: Сергей; last_name: None; username: @kvizer; is_premium: True",
    "1747646842.872899": "223852270; first_name: Сергей; last_name: None; username: @kvizer; is_premium: True",
    "1747646848.9302106": "223852270; first_name: Сергей; last_name: None; username: @kvizer; is_premium: True",
    "1747648851.084077": "223852270; first_name: Сергей; last_name: None; username: @kvizer; is_premium: True",
    "1747652741.9781697": "223852270; first_name: Сергей; last_name: None; username: @kvizer; is_premium: True",
    "1747654248.75766": "223852270; first_name: Сергей; last_name: None; username: @kvizer; is_premium: True",
    "1747659515.4147253": "762352339; first_name: Eery; last_name: None; username: @Eery365; is_premium: True",
    "1747659734.896213": "762352339; first_name: Eery; last_name: None; username: @Eery365; is_premium: True",
    "1747660808.9752343": "223852270; first_name: Сергей; last_name: None; username: @kvizer; is_premium: True",
    "1747660850.6073806": "223852270; first_name: Сергей; last_name: None; username: @kvizer; is_premium: True",
    "1747660855.9158545": "223852270; first_name: Сергей; last_name: None; username: @kvizer; is_premium: True",
    "1747660863.1290915": "223852270; first_name: Сергей; last_name: None; username: @kvizer; is_premium: True",
    "1747660867.8673434": "223852270; first_name: Сергей; last_name: None; username: @kvizer; is_premium: True",
    "1747660882.3459928": "223852270; first_name: Сергей; last_name: None; username: @kvizer; is_premium: True",
    "1747661024.816646": "223852270; first_name: Сергей; last_name: None; username: @kvizer; is_premium: True",
    "1747661036.0756245": "223852270; first_name: Сергей; last_name: None; username: @kvizer; is_premium: True",
    "1747661038.473936": "223852270; first_name: Сергей; last_name: None; username: @kvizer; is_premium: True",
    "1747661068.096348": "223852270; first_name: Сергей; last_name: None; username: @kvizer; is_premium: True",
    "1747661076.2534306": "223852270; first_name: Сергей; last_name: None; username: @kvizer; is_premium: True",
    "1747661079.4518325": "223852270; first_name: Сергей; last_name: None; username: @kvizer; is_premium: True",
    "1747661081.157958": "223852270; first_name: Сергей; last_name: None; username: @kvizer; is_premium: True",
    "1747661097.6960676": "223852270; first_name: Сергей; last_name: None; username: @kvizer; is_premium: True",
    "1747661101.023356": "223852270; first_name: Сергей; last_name: None; username: @kvizer; is_premium: True",
    "1747662610.1493416": "223852270; first_name: Сергей; last_name: None; username: @kvizer; is_premium: True",
    "1747662637.2118049": "223852270; first_name: Сергей; last_name: None; username: @kvizer; is_premium: True",
    "1747662676.2387612": "223852270; first_name: Сергей; last_name: None; username: @kvizer; is_premium: True",
    "1747662683.0624132": "223852270; first_name: Сергей; last_name: None; username: @kvizer; is_premium: True",
    "1747662686.7599542": "223852270; first_name: Сергей; last_name: None; username: @kvizer; is_premium: True",
    "1747662693.83477": "223852270; first_name: Сергей; last_name: None; username: @kvizer; is_premium: True",
    "1747662701.196334": "223852270; first_name: Сергей; last_name: None; username: @kvizer; is_premium: True",
    "1747662703.6534758": "223852270; first_name: Сергей; last_name: None; username: @kvizer; is_premium: True",
    "1747662705.670432": "223852270; first_name: Сергей; last_name: None; username: @kvizer; is_premium: True",
    "1747662709.5733783": "223852270; first_name: Сергей; last_name: None; username: @kvizer; is_premium: True",
    "1747662734.5059996": "223852270; first_name: Сергей; last_name: None; username: @kvizer; is_premium: True",
    "1747662757.0511436": "223852270; first_name: Сергей; last_name: None; username: @kvizer; is_premium: True",
    "1747662761.2404892": "223852270; first_name: Сергей; last_name: None; username: @kvizer; is_premium: True",
    "1747662764.4544358": "223852270; first_name: Сергей; last_name: None; username: @kvizer; is_premium: True",
    "1747662778.2911918": "223852270; first_name: Сергей; last_name: None; username: @kvizer; is_premium: True",
    "1747662784.9419622": "223852270; first_name: Сергей; last_name: None; username: @kvizer; is_premium: True",
    "1747662789.655913": "223852270; first_name: Сергей; last_name: None; username: @kvizer; is_premium: True",
    "1747662810.130354": "223852270; first_name: Сергей; last_name: None; username: @kvizer; is_premium: True",
    "1747662819.500029": "223852270; first_name: Сергей; last_name: None; username: @kvizer; is_premium: True",
    "1747666811.863043": "223852270; first_name: Сергей; last_name: None; username: @kvizer; is_premium: True",
    "1747666849.5256786": "223852270; first_name: Сергей; last_name: None; username: @kvizer; is_premium: True",
    "1747666859.1684432": "223852270; first_name: Сергей; last_name: None; username: @kvizer; is_premium: True",
    "1747666863.7946265": "223852270; first_name: Сергей; last_name: None; username: @kvizer; is_premium: True",
    "1747666871.3612032": "223852270; first_name: Сергей; last_name: None; username: @kvizer; is_premium: True",
    "1747666876.1060085": "223852270; first_name: Сергей; last_name: None; username: @kvizer; is_premium: True",
    "1747666888.4889715": "223852270; first_name: Сергей; last_name: None; username: @kvizer; is_premium: True",
    "1747666894.6714458": "223852270; first_name: Сергей; last_name: None; username: @kvizer; is_premium: True",
    "1747666902.3995516": "223852270; first_name: Сергей; last_name: None; username: @kvizer; is_premium: True",
    "1747666929.781218": "223852270; first_name: Сергей; last_name: None; username: @kvizer; is_premium: True",
    "1747666934.7818363": "223852270; first_name: Сергей; last_name: None; username: @kvizer; is_premium: True",
    "1747666936.3453295": "223852270; first_name: Сергей; last_name: None; username: @kvizer; is_premium: True",
    "1747666937.8950167": "223852270; first_name: Сергей; last_name: None; username: @kvizer; is_premium: True",
    "1747666940.4590573": "223852270; first_name: Сергей; last_name: None; username: @kvizer; is_premium: True",
    "1747666942.1016815": "223852270; first_name: Сергей; last_name: None; username: @kvizer; is_premium: True",
    "1747666943.461485": "223852270; first_name: Сергей; last_name: None; username: @kvizer; is_premium: True",
    "1747666945.0224612": "223852270; first_name: Сергей; last_name: None; username: @kvizer; is_premium: True",
    "1747666946.5172234": "223852270; first_name: Сергей; last_name: None; username: @kvizer; is_premium: True",
    "1747666947.9280837": "223852270; first_name: Сергей; last_name: None; username: @kvizer; is_premium: True",
    "1747666949.5013232": "223852270; first_name: Сергей; last_name: None; username: @kvizer; is_premium: True",
    "1747666955.7513154": "223852270; first_name: Сергей; last_name: None; username: @kvizer; is_premium: True",
    "1747666958.61689": "223852270; first_name: Сергей; last_name: None; username: @kvizer; is_premium: True",
    "1747666961.1056125": "223852270; first_name: Сергей; last_name: None; username: @kvizer; is_premium: True",
    "1747666962.848289": "223852270; first_name: Сергей; last_name: None; username: @kvizer; is_premium: True",
    "1747666964.412277": "223852270; first_name: Сергей; last_name: None; username: @kvizer; is_premium: True",
    "1747666965.8607419": "223852270; first_name: Сергей; last_name: None; username: @kvizer; is_premium: True",
    "1747666967.4904685": "223852270; first_name: Сергей; last_name: None; username: @kvizer; is_premium: True",
    "1747666969.6761332": "223852270; first_name: Сергей; last_name: None; username: @kvizer; is_premium: True",
    "1747666971.7044575": "223852270; first_name: Сергей; last_name: None; username: @kvizer; is_premium: True",
    "1747666973.0836043": "223852270; first_name: Сергей; last_name: None; username: @kvizer; is_premium: True",
    "1747666974.335422": "223852270; first_name: Сергей; last_name: None; username: @kvizer; is_premium: True",
    "1747666975.779374": "223852270; first_name: Сергей; last_name: None; username: @kvizer; is_premium: True",
    "1747666977.1785417": "223852270; first_name: Сергей; last_name: None; username: @kvizer; is_premium: True",
    "1747666978.5022173": "223852270; first_name: Сергей; last_name: None; username: @kvizer; is_premium: True",
    "1747666980.2376406": "223852270; first_name: Сергей; last_name: None; username: @kvizer; is_premium: True",
    "1747666982.9563546": "223852270; first_name: Сергей; last_name: None; username: @kvizer; is_premium: True",
    "1747666984.6064959": "223852270; first_name: Сергей; last_name: None; username: @kvizer; is_premium: True",
    "1747666986.2185042": "223852270; first_name: Сергей; last_name: None; username: @kvizer; is_premium: True",
    "1747666987.6621714": "223852270; first_name: Сергей; last_name: None; username: @kvizer; is_premium: True",
    "1747666989.2277792": "223852270; first_name: Сергей; last_name: None; username: @kvizer; is_premium: True",
    "1747666990.8113248": "223852270; first_name: Сергей; last_name: None; username: @kvizer; is_premium: True",
    "1747666992.484075": "223852270; first_name: Сергей; last_name: None; username: @kvizer; is_premium: True",
    "1747668092.7487652": "223852270; first_name: Сергей; last_name: None; username: @kvizer; is_premium: True",
    "1747683164.6690173": "223852270; first_name: Сергей; last_name: None; username: @kvizer; is_premium: True",
    "1747683193.5242693": "223852270; first_name: Сергей; last_name: None; username: @kvizer; is_premium: True",
    "1747687044.0329626": "223852270; first_name: Сергей; last_name: None; username: @kvizer; is_premium: True",
    "1747687044.2151737": "223852270; first_name: Сергей; last_name: None; username: @kvizer; is_premium: True",
    "1747687057.3782396": "223852270; first_name: Сергей; last_name: None; username: @kvizer; is_premium: True",
    "1747687065.8672433": "223852270; first_name: Сергей; last_name: None; username: @kvizer; is_premium: True",
    "1747687070.1653583": "223852270; first_name: Сергей; last_name: None; username: @kvizer; is_premium: True",
    "1747687095.9637806": "223852270; first_name: Сергей; last_name: None; username: @kvizer; is_premium: True",
    "1747687138.1694446": "223852270; first_name: Сергей; last_name: None; username: @kvizer; is_premium: True"
}